setup.py
ria_probability/Binomialdistribution.py
ria_probability/Gaussiandistribution.py
ria_probability/Generaldistribution.py
ria_probability/__init__.py
ria_probability.egg-info/PKG-INFO
ria_probability.egg-info/SOURCES.txt
ria_probability.egg-info/dependency_links.txt
ria_probability.egg-info/not-zip-safe
ria_probability.egg-info/top_level.txt