Metadata-Version: 1.0
Name: ria-probability
Version: 0.1
Summary: Gaussian and Binomial distributions
Home-page: UNKNOWN
Author: Alfonso Ridolfo
Author-email: alfonso.ridolfo@gmail.com
License: UNKNOWN
Platform: UNKNOWN
